dice_stats/__init__.py
dice_stats/_types.py
dice_stats/dice.py
dice_stats/display.py
dice_stats/py.typed
dice_stats/range.py
dice_stats/_magic/__init__.py
dice_stats/_magic/base_dice.py
dice_stats/_magic/basic.py
dice_stats/_magic/mapping.py
dice_stats/_magic/numeric.py
dice_stats-1.1.0.dist-info/LICENSE
dice_stats-1.1.0.dist-info/METADATA
dice_stats-1.1.0.dist-info/WHEEL
dice_stats-1.1.0.dist-info/top_level.txt
dice_stats-1.1.0.dist-info/RECORD
