Metadata-Version: 2.1
Name: dice-stats
Version: 1.1.0
Summary: Get statistics for rolling dice
Home-page: https://peilonrayz.github.io/dice_stats
Author: Peilonrayz
Author-email: peilonrayz@gmail.com
License: MIT
Project-URL: Bug Tracker, https://github.com/Peilonrayz/dice_stats/issues
Project-URL: Documentation, https://peilonrayz.github.io/dice_stats
Project-URL: Source Code, https://github.com/Peilonrayz/dice_stats
Platform: UNKNOWN
Classifier: Development Status :: 3 - Alpha
Classifier: Environment :: Console
Classifier: Intended Audience :: Developers
Classifier: License :: OSI Approved :: MIT License
Classifier: Operating System :: OS Independent
Classifier: Programming Language :: Python :: 3.7
Classifier: Programming Language :: Python :: 3.8
Provides-Extra: optional
Requires-Dist: numpy ; extra == 'optional'
Requires-Dist: matplotlib ; extra == 'optional'
